README.rst
setup.py
infi/__init__.py
infi.conf.egg-info/PKG-INFO
infi.conf.egg-info/SOURCES.txt
infi.conf.egg-info/dependency_links.txt
infi.conf.egg-info/namespace_packages.txt
infi.conf.egg-info/requires.txt
infi.conf.egg-info/top_level.txt
infi/conf/__init__.py
infi/conf/__version__.py
infi/conf/config.py
infi/conf/exceptions.py
infi/conf/python3_compat.py
infi/conf/utils.py