Metadata-Version: 1.1
Name: infi.conf
Version: 0.0.15
Summary: Generic configuration mechanism
Home-page: https://github.com/vmalloc/infi.conf
Author: Rotem Yaari
Author-email: vmalloc@gmail.com
License: BSD
Platform: UNKNOWN
Classifier: Development Status :: 4 - Beta
Classifier: Intended Audience :: Developers
Classifier: License :: OSI Approved :: BSD License
Classifier: Programming Language :: Python :: 2.7
